pygmat/__init__.py
pygmat/pygmat.py
pygmat-0.0.3.dist-info/METADATA
pygmat-0.0.3.dist-info/WHEEL
pygmat-0.0.3.dist-info/licenses/LICENSE
pygmat-0.0.3.dist-info/RECORD
