Metadata-Version: 2.1
Name: pygmat
Version: 0.0.3
Summary: A package to interface the script creation for NASA General Mission Analysis Tool -- GMAT
Project-URL: Homepage, https://github.com/pypa/pygmat
Project-URL: Issues, https://github.com/pypa/pygmat/issues
Author-email: Carlos LG Batista <clgbatista@pm.me>
License: MIT License
License-File: LICENSE
Keywords: gmat,nasa,space
Classifier: Development Status :: 4 - Beta
Classifier: License :: OSI Approved :: MIT License
Classifier: Operating System :: OS Independent
Classifier: Programming Language :: Python :: 3
Requires-Python: >=3.10
